django_routes_search/__about__.py
django_routes_search/__init__.py
django_routes_search-0.0.1.dist-info/METADATA
django_routes_search-0.0.1.dist-info/WHEEL
django_routes_search-0.0.1.dist-info/licenses/LICENSE.txt
django_routes_search-0.0.1.dist-info/RECORD
